py_safe_loader/__init__.py
py_safe_loader/loader.py
py_safe_loader-0.1.0.dist-info/METADATA
py_safe_loader-0.1.0.dist-info/WHEEL
py_safe_loader-0.1.0.dist-info/top_level.txt
py_safe_loader-0.1.0.dist-info/RECORD
