Metadata-Version: 2.4
Name: py-safe-loader
Version: 0.1.0
Summary: Reusable SafeLoader for safe imports and execution
Author-email: Moganthkumar <moganthkumar24405@gmail.com>
License: MIT
Requires-Python: >=3.8
